tkloguru/__init__.py
tkloguru-0.1.2.dist-info/LICENSE
tkloguru-0.1.2.dist-info/METADATA
tkloguru-0.1.2.dist-info/WHEEL
tkloguru-0.1.2.dist-info/RECORD
