Metadata-Version: 2.1
Name: tkloguru
Version: 0.1.2
Summary: A custom Tkinter widget that displays Loguru log messages in real-time with support for styling and colors. Monitor application logs directly within your Tkinter GUI.
License: MIT
Author: Aareon Sullivan
Author-email: askully13@gmail.com
Requires-Python: >=3.10,<4.0
Classifier: Development Status :: 3 - Alpha
Classifier: Intended Audience :: Developers
Classifier: License :: OSI Approved :: MIT License
Classifier: Operating System :: OS Independent
Classifier: Programming Language :: Python :: 3
Classifier: Programming Language :: Python :: 3.10
Classifier: Programming Language :: Python :: 3.11
Classifier: Programming Language :: Python :: 3.12
Classifier: Programming Language :: Python :: 3.6
Classifier: Programming Language :: Python :: 3.7
Classifier: Programming Language :: Python :: 3.8
Classifier: Programming Language :: Python :: 3.9
Requires-Dist: loguru (>=0.7.2,<0.8.0)
Project-URL: Bug Tracker, https://github.com/Aareon/TkLoguru/issues
Project-URL: Homepage, https://github.com/Aareon/TkLoguru
